dffs/__init__.py
dffs/_version.py
dffs/cli.py
dffs/shell_integration_cli.py
dffs/utils.py
dffs/comm_x/__init__.py
dffs/commands/__init__.py
dffs/commands/shell_integration.py
dffs/diff_x/__init__.py
dffs/git_diff_x/__init__.py
dffs/shell/dffs.bash
dffs-0.1.5.dist-info/METADATA
dffs-0.1.5.dist-info/WHEEL
dffs-0.1.5.dist-info/entry_points.txt
dffs-0.1.5.dist-info/licenses/LICENSE
dffs-0.1.5.dist-info/RECORD
