Metadata-Version: 2.4
Name: dffs
Version: 0.1.5
Summary: Pipe and diff files: execute shell pipelines against multiple inputs, diff/compare/join results.
Project-URL: Homepage, https://github.com/runsascoded/dffs
Project-URL: Author URL, https://github.com/ryan-williams
Author-email: Ryan Williams <ryan@runsascoded.com>
License: MIT
License-File: LICENSE
Requires-Python: >=3.10
Requires-Dist: click
Requires-Dist: utz>=0.21.5
Provides-Extra: ci
Requires-Dist: mdcmd>=0.7.4; extra == 'ci'
Requires-Dist: pytest-cov>=4.0.0; extra == 'ci'
Requires-Dist: pytest>=7.0.0; extra == 'ci'
Provides-Extra: test
Requires-Dist: pytest-cov>=4.0.0; extra == 'test'
Requires-Dist: pytest>=7.0.0; extra == 'test'
